kodra/__init__.py
kodra/client.py
kodra/test/__init__.py
kodra/test/test_kodra.py
kodra-0.0.9.dist-info/LICENSE
kodra-0.0.9.dist-info/METADATA
kodra-0.0.9.dist-info/WHEEL
kodra-0.0.9.dist-info/top_level.txt
kodra-0.0.9.dist-info/RECORD
