Metadata-Version: 2.1
Name: kodra
Version: 0.0.9
Summary: Kodra Python Client
Author-email: Kodra Technologies <support@kodra.ai>
Project-URL: Homepage, https://www.kodra.ai
Classifier: Programming Language :: Python :: 3
Classifier: License :: OSI Approved :: Apache Software License
Classifier: Operating System :: OS Independent
Requires-Python: >=3.7
License-File: LICENSE
Requires-Dist: pandas
Requires-Dist: requests
Requires-Dist: requests-toolbelt
Requires-Dist: tqdm
